simple_bencher/__init__.py
simple_bencher/bencher.py
simple_bencher/statistics.py
SimpleBencher-0.6.0.dist-info/LICENSE
SimpleBencher-0.6.0.dist-info/METADATA
SimpleBencher-0.6.0.dist-info/WHEEL
SimpleBencher-0.6.0.dist-info/top_level.txt
SimpleBencher-0.6.0.dist-info/RECORD
