Metadata-Version: 2.1
Name: SimpleBencher
Version: 0.6.0
Summary: Benchmarking Suite
Home-page: https://github.com/swip3798/Bencher
Author: Christian Schweigel
Author-email: 
License: UNKNOWN
Platform: UNKNOWN
Classifier: Programming Language :: Python :: 3
Classifier: Programming Language :: Python :: 3 :: Only
Classifier: Operating System :: OS Independent
Classifier: Development Status :: 3 - Alpha
